Metadata-Version: 1.1
Name: django-email-interceptor
Version: 0.1
Summary: Simple backend to intercept emails during development
Home-page: https://github.com/Brobin/django-email-interceptor
Author: Tobin Brown
Author-email: tobin@brobin.me
License: MIT
Platform: UNKNOWN
Classifier: Framework :: Django
Classifier: Intended Audience :: Developers
Classifier: Operating System :: OS Independent
Classifier: Programming Language :: Python
Classifier: Programming Language :: Python :: 3
Classifier: Programming Language :: Python :: 3.4
Classifier: Programming Language :: Python :: 3.5
Classifier: Topic :: Software Development :: Libraries :: Python Modules
